{
    "icono": "FormatColorText",
    "module": "texto",
    "titulo": "Textos",
    "sub": "",
    "padre": "",
    "menu": [
        {"field": "new", "titulo": "Nuevo"},
        {"field": "excel", "titulo": "Exportar a excel"},
        {"field": "regenerar", "titulo": "Regenerar imagenes"}
    ],
    "mostrar": [
        {"field": "orden", "titulo": "Orden", "tipo": "text"},
        {"field": "titulo", "titulo": "Titulo", "tipo": "text"},
        {"field": "texto", "titulo": "Texto", "tipo": "text"},
        {"field": "estado", "titulo": "Estado", "tipo": "active"},
        {"field": "copy", "titulo": "Copiar", "tipo": "action"},
        {"field": "url_detalle", "titulo": "Editar", "tipo": "link"},
        {"field": "delete", "titulo": "Eliminar", "tipo": "delete"}
    ],
    "detalle": [
        {"field": "titulo", "titulo": "Titulo", "tipo": "text"},
        {"field": "descripcion", "titulo": "Descripcion", "tipo": "editor"},
        {"field": "texto", "titulo": "Texto", "tipo": "text"},
        {"field": "mapa", "titulo": "Mapa", "tipo": "map"},
        {"field": "orden", "titulo": "Orden", "tipo": "number"},
        {"field": "estado", "titulo": "Estado", "tipo": "active"}
    ],
    "orden": 11,
    "estado": false,
    "aside": true,
    "tipos": true,
    "hijo": [
        {
            "tipo": 1,
            "titulo": "Datos de contacto",
            "permisos": {
                "1": {
                    "estado": true,
                    "menu": {"new": true, "excel": false, "regenerar": false},
                    "mostrar": {"usuario": true, "estado": true, "copy": false, "url_detalle": true, "delete": true, "idmediopago": false, "orden": true, "titulo": true, "idigtotal": false, "fecha": true, "tag": true, "cantidad": true, "idadministrador": true, "nombre": true, "email": true, "foto": true, "idighashtag": true, "hashtag": true, "pk": true, "username": true, "full_name": true, "profile_url": true, "profile_pic_url": true, "follower": true, "following": true, "favorito": true, "update": true, "idprofile": true, "idusuario": false, "url_sub": true, "idseccion": false, "destacado": false, "idseo": false, "url": true, "banner": false, "menu": false, "submenu": false, "idpedidoestado": false, "color": true, "idusuariodireccion": false, "idproductocategoria": false, "url_children": true, "variable": true, "valor": true, "idproducto": false, "texto": false},
                    "detalle": {"usuario": true, "password": true, "estado": true, "titulo": true, "resumen": false, "descripcion": false, "orden": true, "tag": true, "fecha": true, "cantidad": true, "foto": true, "nombre": true, "email": true, "hashtag": true, "following": true, "follower": true, "removed": true, "eficiencia": true, "eficiencia2": true, "total": true, "tipo": true, "telefono": true, "url": false, "subtitulo": true, "archivo": false, "idseccioncategoria": false, "keywords": false, "metadescripcion": false, "destacado": false, "banner": false, "modulo_front": false, "modulo_back": false, "tipo_modulo": false, "link_menu": false, "menu": false, "submenu": false, "color": true, "direccion": true, "idcomuna": true, "villa": true, "edificio": true, "departamento": true, "condominio": true, "casa": true, "empresa": true, "referencias": true, "descuento": false, "descuento_fecha": false, "idpadre": true, "variable": true, "valor": true, "codigo": false, "precio": false, "stock": false, "idproductocategoria": false, "texto": false, "mapa": true}
                },
                "2": {
                    "estado": true,
                    "menu": {"new": true, "excel": false, "regenerar": false},
                    "mostrar": {"usuario": true, "estado": true, "copy": false, "url_detalle": true, "delete": true, "idmediopago": false, "orden": true, "titulo": true, "idigtotal": false, "fecha": true, "tag": true, "cantidad": true, "idadministrador": true, "nombre": true, "email": true, "foto": true, "idighashtag": true, "hashtag": true, "pk": true, "username": true, "full_name": true, "profile_url": true, "profile_pic_url": true, "follower": true, "following": true, "favorito": true, "update": true, "idprofile": true, "idusuario": false, "url_sub": true, "idseccion": false, "destacado": false, "idseo": false, "url": true, "banner": false, "menu": false, "submenu": false, "idpedidoestado": false, "color": true, "idusuariodireccion": false, "idproductocategoria": false, "url_children": true, "variable": true, "valor": true, "idproducto": false, "texto": false},
                    "detalle": {"usuario": true, "password": true, "estado": true, "titulo": true, "resumen": false, "descripcion": false, "orden": true, "tag": true, "fecha": true, "cantidad": true, "foto": true, "nombre": true, "email": true, "hashtag": true, "following": true, "follower": true, "removed": true, "eficiencia": true, "eficiencia2": true, "total": true, "tipo": true, "telefono": true, "url": false, "subtitulo": true, "archivo": false, "idseccioncategoria": false, "keywords": false, "metadescripcion": false, "destacado": false, "banner": false, "modulo_front": false, "modulo_back": false, "tipo_modulo": false, "link_menu": false, "menu": false, "submenu": false, "color": true, "direccion": true, "idcomuna": true, "villa": true, "edificio": true, "departamento": true, "condominio": true, "casa": true, "empresa": true, "referencias": true, "descuento": false, "descuento_fecha": false, "idpadre": true, "variable": true, "valor": true, "codigo": false, "precio": false, "stock": false, "idproductocategoria": false, "texto": false, "mapa": true}
                },
                "3": {
                    "estado": true,
                    "menu": {"new": true, "excel": false, "regenerar": false},
                    "mostrar": {"usuario": true, "estado": true, "copy": false, "url_detalle": true, "delete": true, "idmediopago": false, "orden": true, "titulo": true, "idigtotal": false, "fecha": true, "tag": true, "cantidad": true, "idadministrador": true, "nombre": true, "email": true, "foto": true, "idighashtag": true, "hashtag": true, "pk": true, "username": true, "full_name": true, "profile_url": true, "profile_pic_url": true, "follower": true, "following": true, "favorito": true, "update": true, "idprofile": true, "idusuario": false, "url_sub": true, "idseccion": false, "destacado": false, "idseo": false, "url": true, "banner": false, "menu": false, "submenu": false, "idpedidoestado": false, "color": true, "idusuariodireccion": false, "idproductocategoria": false, "url_children": true, "variable": true, "valor": true, "idproducto": false, "texto": false},
                    "detalle": {"usuario": true, "password": true, "estado": true, "titulo": true, "resumen": false, "descripcion": false, "orden": true, "tag": true, "fecha": true, "cantidad": true, "foto": true, "nombre": true, "email": true, "hashtag": true, "following": true, "follower": true, "removed": true, "eficiencia": true, "eficiencia2": true, "total": true, "tipo": true, "telefono": true, "url": false, "subtitulo": true, "archivo": false, "idseccioncategoria": false, "keywords": false, "metadescripcion": false, "destacado": false, "banner": false, "modulo_front": false, "modulo_back": false, "tipo_modulo": false, "link_menu": false, "menu": false, "submenu": false, "color": true, "direccion": true, "idcomuna": true, "villa": true, "edificio": true, "departamento": true, "condominio": true, "casa": true, "empresa": true, "referencias": true, "descuento": false, "descuento_fecha": false, "idpadre": true, "variable": true, "valor": true, "codigo": false, "precio": false, "stock": false, "idproductocategoria": false, "texto": false, "mapa": true}
                }
            },
            "orden": 1,
            "aside": true,
            "hijos": false
        },
        {
            "tipo": 2,
            "titulo": "Redes sociales",
            "permisos": {
                "1": {
                    "estado": true,
                    "menu": {"new": true, "excel": false, "regenerar": false},
                    "mostrar": {"usuario": true, "estado": true, "copy": false, "url_detalle": true, "delete": true, "idmediopago": false, "orden": true, "titulo": true, "idigtotal": false, "fecha": true, "tag": true, "cantidad": true, "idadministrador": true, "nombre": true, "email": true, "foto": true, "idighashtag": true, "hashtag": true, "pk": true, "username": true, "full_name": true, "profile_url": true, "profile_pic_url": true, "follower": true, "following": true, "favorito": true, "update": true, "idprofile": true, "idusuario": false, "url_sub": true, "idseccion": false, "destacado": false, "idseo": false, "url": true, "banner": false, "menu": false, "submenu": false, "idpedidoestado": false, "color": true, "idusuariodireccion": false, "idproductocategoria": false, "url_children": true, "variable": true, "valor": true, "idproducto": false, "texto": false},
                    "detalle": {"usuario": true, "password": true, "estado": true, "titulo": true, "resumen": false, "descripcion": false, "orden": true, "tag": true, "fecha": true, "cantidad": true, "foto": true, "nombre": true, "email": true, "hashtag": true, "following": true, "follower": true, "removed": true, "eficiencia": true, "eficiencia2": true, "total": true, "tipo": true, "telefono": true, "url": false, "subtitulo": true, "archivo": false, "idseccioncategoria": false, "keywords": false, "metadescripcion": false, "destacado": false, "banner": false, "modulo_front": false, "modulo_back": false, "tipo_modulo": false, "link_menu": false, "menu": false, "submenu": false, "color": true, "direccion": true, "idcomuna": true, "villa": true, "edificio": true, "departamento": true, "condominio": true, "casa": true, "empresa": true, "referencias": true, "descuento": false, "descuento_fecha": false, "idpadre": true, "variable": true, "valor": true, "codigo": false, "precio": false, "stock": false, "idproductocategoria": false, "texto": false, "mapa": true}
                },
                "2": {
                    "estado": true,
                    "menu": {"new": true, "excel": false, "regenerar": false},
                    "mostrar": {"usuario": true, "estado": true, "copy": false, "url_detalle": true, "delete": true, "idmediopago": false, "orden": true, "titulo": true, "idigtotal": false, "fecha": true, "tag": true, "cantidad": true, "idadministrador": true, "nombre": true, "email": true, "foto": true, "idighashtag": true, "hashtag": true, "pk": true, "username": true, "full_name": true, "profile_url": true, "profile_pic_url": true, "follower": true, "following": true, "favorito": true, "update": true, "idprofile": true, "idusuario": false, "url_sub": true, "idseccion": false, "destacado": false, "idseo": false, "url": true, "banner": false, "menu": false, "submenu": false, "idpedidoestado": false, "color": true, "idusuariodireccion": false, "idproductocategoria": false, "url_children": true, "variable": true, "valor": true, "idproducto": false, "texto": false},
                    "detalle": {"usuario": true, "password": true, "estado": true, "titulo": true, "resumen": false, "descripcion": false, "orden": true, "tag": true, "fecha": true, "cantidad": true, "foto": true, "nombre": true, "email": true, "hashtag": true, "following": true, "follower": true, "removed": true, "eficiencia": true, "eficiencia2": true, "total": true, "tipo": true, "telefono": true, "url": false, "subtitulo": true, "archivo": false, "idseccioncategoria": false, "keywords": false, "metadescripcion": false, "destacado": false, "banner": false, "modulo_front": false, "modulo_back": false, "tipo_modulo": false, "link_menu": false, "menu": false, "submenu": false, "color": true, "direccion": true, "idcomuna": true, "villa": true, "edificio": true, "departamento": true, "condominio": true, "casa": true, "empresa": true, "referencias": true, "descuento": false, "descuento_fecha": false, "idpadre": true, "variable": true, "valor": true, "codigo": false, "precio": false, "stock": false, "idproductocategoria": false, "texto": false, "mapa": true}
                },
                "3": {
                    "estado": true,
                    "menu": {"new": true, "excel": false, "regenerar": false},
                    "mostrar": {"usuario": true, "estado": true, "copy": false, "url_detalle": true, "delete": true, "idmediopago": false, "orden": true, "titulo": true, "idigtotal": false, "fecha": true, "tag": true, "cantidad": true, "idadministrador": true, "nombre": true, "email": true, "foto": true, "idighashtag": true, "hashtag": true, "pk": true, "username": true, "full_name": true, "profile_url": true, "profile_pic_url": true, "follower": true, "following": true, "favorito": true, "update": true, "idprofile": true, "idusuario": false, "url_sub": true, "idseccion": false, "destacado": false, "idseo": false, "url": true, "banner": false, "menu": false, "submenu": false, "idpedidoestado": false, "color": true, "idusuariodireccion": false, "idproductocategoria": false, "url_children": true, "variable": true, "valor": true, "idproducto": false, "texto": false},
                    "detalle": {"usuario": true, "password": true, "estado": true, "titulo": true, "resumen": false, "descripcion": false, "orden": true, "tag": true, "fecha": true, "cantidad": true, "foto": true, "nombre": true, "email": true, "hashtag": true, "following": true, "follower": true, "removed": true, "eficiencia": true, "eficiencia2": true, "total": true, "tipo": true, "telefono": true, "url": false, "subtitulo": true, "archivo": false, "idseccioncategoria": false, "keywords": false, "metadescripcion": false, "destacado": false, "banner": false, "modulo_front": false, "modulo_back": false, "tipo_modulo": false, "link_menu": false, "menu": false, "submenu": false, "color": true, "direccion": true, "idcomuna": true, "villa": true, "edificio": true, "departamento": true, "condominio": true, "casa": true, "empresa": true, "referencias": true, "descuento": false, "descuento_fecha": false, "idpadre": true, "variable": true, "valor": true, "codigo": false, "precio": false, "stock": false, "idproductocategoria": false, "texto": false, "mapa": true}
                }
            },
            "orden": 2,
            "aside": true,
            "hijos": false
        },
        {
            "tipo": 3,
            "titulo": "Textos administrables",
            "permisos": {
                "1": {
                    "estado": true,
                    "menu": {"new": true, "excel": false, "regenerar": false},
                    "mostrar": {"usuario": true, "estado": true, "copy": false, "url_detalle": true, "delete": true, "idmediopago": false, "orden": true, "titulo": true, "idigtotal": false, "fecha": true, "tag": true, "cantidad": true, "idadministrador": true, "nombre": true, "email": true, "foto": true, "idighashtag": true, "hashtag": true, "pk": true, "username": true, "full_name": true, "profile_url": true, "profile_pic_url": true, "follower": true, "following": true, "favorito": true, "update": true, "idprofile": true, "idusuario": false, "url_sub": true, "idseccion": false, "destacado": false, "idseo": false, "url": true, "banner": false, "menu": false, "submenu": false, "idpedidoestado": false, "color": true, "idusuariodireccion": false, "idproductocategoria": false, "url_children": true, "variable": true, "valor": true, "idproducto": false, "texto": false},
                    "detalle": {"usuario": true, "password": true, "estado": true, "titulo": true, "resumen": false, "descripcion": false, "orden": true, "tag": true, "fecha": true, "cantidad": true, "foto": true, "nombre": true, "email": true, "hashtag": true, "following": true, "follower": true, "removed": true, "eficiencia": true, "eficiencia2": true, "total": true, "tipo": true, "telefono": true, "url": false, "subtitulo": true, "archivo": false, "idseccioncategoria": false, "keywords": false, "metadescripcion": false, "destacado": false, "banner": false, "modulo_front": false, "modulo_back": false, "tipo_modulo": false, "link_menu": false, "menu": false, "submenu": false, "color": true, "direccion": true, "idcomuna": true, "villa": true, "edificio": true, "departamento": true, "condominio": true, "casa": true, "empresa": true, "referencias": true, "descuento": false, "descuento_fecha": false, "idpadre": true, "variable": true, "valor": true, "codigo": false, "precio": false, "stock": false, "idproductocategoria": false, "texto": false, "mapa": true}
                },
                "2": {
                    "estado": true,
                    "menu": {"new": true, "excel": false, "regenerar": false},
                    "mostrar": {"usuario": true, "estado": true, "copy": false, "url_detalle": true, "delete": true, "idmediopago": false, "orden": true, "titulo": true, "idigtotal": false, "fecha": true, "tag": true, "cantidad": true, "idadministrador": true, "nombre": true, "email": true, "foto": true, "idighashtag": true, "hashtag": true, "pk": true, "username": true, "full_name": true, "profile_url": true, "profile_pic_url": true, "follower": true, "following": true, "favorito": true, "update": true, "idprofile": true, "idusuario": false, "url_sub": true, "idseccion": false, "destacado": false, "idseo": false, "url": true, "banner": false, "menu": false, "submenu": false, "idpedidoestado": false, "color": true, "idusuariodireccion": false, "idproductocategoria": false, "url_children": true, "variable": true, "valor": true, "idproducto": false, "texto": false},
                    "detalle": {"usuario": true, "password": true, "estado": true, "titulo": true, "resumen": false, "descripcion": false, "orden": true, "tag": true, "fecha": true, "cantidad": true, "foto": true, "nombre": true, "email": true, "hashtag": true, "following": true, "follower": true, "removed": true, "eficiencia": true, "eficiencia2": true, "total": true, "tipo": true, "telefono": true, "url": false, "subtitulo": true, "archivo": false, "idseccioncategoria": false, "keywords": false, "metadescripcion": false, "destacado": false, "banner": false, "modulo_front": false, "modulo_back": false, "tipo_modulo": false, "link_menu": false, "menu": false, "submenu": false, "color": true, "direccion": true, "idcomuna": true, "villa": true, "edificio": true, "departamento": true, "condominio": true, "casa": true, "empresa": true, "referencias": true, "descuento": false, "descuento_fecha": false, "idpadre": true, "variable": true, "valor": true, "codigo": false, "precio": false, "stock": false, "idproductocategoria": false, "texto": false, "mapa": true}
                },
                "3": {
                    "estado": true,
                    "menu": {"new": true, "excel": false, "regenerar": false},
                    "mostrar": {"usuario": true, "estado": true, "copy": false, "url_detalle": true, "delete": true, "idmediopago": false, "orden": true, "titulo": true, "idigtotal": false, "fecha": true, "tag": true, "cantidad": true, "idadministrador": true, "nombre": true, "email": true, "foto": true, "idighashtag": true, "hashtag": true, "pk": true, "username": true, "full_name": true, "profile_url": true, "profile_pic_url": true, "follower": true, "following": true, "favorito": true, "update": true, "idprofile": true, "idusuario": false, "url_sub": true, "idseccion": false, "destacado": false, "idseo": false, "url": true, "banner": false, "menu": false, "submenu": false, "idpedidoestado": false, "color": true, "idusuariodireccion": false, "idproductocategoria": false, "url_children": true, "variable": true, "valor": true, "idproducto": false, "texto": false},
                    "detalle": {"usuario": true, "password": true, "estado": true, "titulo": true, "resumen": false, "descripcion": false, "orden": true, "tag": true, "fecha": true, "cantidad": true, "foto": true, "nombre": true, "email": true, "hashtag": true, "following": true, "follower": true, "removed": true, "eficiencia": true, "eficiencia2": true, "total": true, "tipo": true, "telefono": true, "url": false, "subtitulo": true, "archivo": false, "idseccioncategoria": false, "keywords": false, "metadescripcion": false, "destacado": false, "banner": false, "modulo_front": false, "modulo_back": false, "tipo_modulo": false, "link_menu": false, "menu": false, "submenu": false, "color": true, "direccion": true, "idcomuna": true, "villa": true, "edificio": true, "departamento": true, "condominio": true, "casa": true, "empresa": true, "referencias": true, "descuento": false, "descuento_fecha": false, "idpadre": true, "variable": true, "valor": true, "codigo": false, "precio": false, "stock": false, "idproductocategoria": false, "texto": false, "mapa": true}
                }
            },
            "orden": 3,
            "aside": true,
            "hijos": false
        },
        {
            "tipo": 4,
            "titulo": "Mapas",
            "permisos": {
                "1": {
                    "estado": true,
                    "menu": {"new": true, "excel": false, "regenerar": false},
                    "mostrar": {"usuario": true, "estado": true, "copy": false, "url_detalle": true, "delete": true, "idmediopago": false, "orden": true, "titulo": true, "idigtotal": false, "fecha": true, "tag": true, "cantidad": true, "idadministrador": true, "nombre": true, "email": true, "foto": true, "idighashtag": true, "hashtag": true, "pk": true, "username": true, "full_name": true, "profile_url": true, "profile_pic_url": true, "follower": true, "following": true, "favorito": true, "update": true, "idprofile": true, "idusuario": false, "url_sub": true, "idseccion": false, "destacado": false, "idseo": false, "url": true, "banner": false, "menu": false, "submenu": false, "idpedidoestado": false, "color": true, "idusuariodireccion": false, "idproductocategoria": false, "url_children": true, "variable": true, "valor": true, "idproducto": false, "texto": false},
                    "detalle": {"usuario": true, "password": true, "estado": true, "titulo": true, "resumen": false, "descripcion": false, "orden": true, "tag": true, "fecha": true, "cantidad": true, "foto": true, "nombre": true, "email": true, "hashtag": true, "following": true, "follower": true, "removed": true, "eficiencia": true, "eficiencia2": true, "total": true, "tipo": true, "telefono": true, "url": false, "subtitulo": true, "archivo": false, "idseccioncategoria": false, "keywords": false, "metadescripcion": false, "destacado": false, "banner": false, "modulo_front": false, "modulo_back": false, "tipo_modulo": false, "link_menu": false, "menu": false, "submenu": false, "color": true, "direccion": true, "idcomuna": true, "villa": true, "edificio": true, "departamento": true, "condominio": true, "casa": true, "empresa": true, "referencias": true, "descuento": false, "descuento_fecha": false, "idpadre": true, "variable": true, "valor": true, "codigo": false, "precio": false, "stock": false, "idproductocategoria": false, "texto": false, "mapa": true}
                },
                "2": {
                    "estado": true,
                    "menu": {"new": true, "excel": false, "regenerar": false},
                    "mostrar": {"usuario": true, "estado": true, "copy": false, "url_detalle": true, "delete": true, "idmediopago": false, "orden": true, "titulo": true, "idigtotal": false, "fecha": true, "tag": true, "cantidad": true, "idadministrador": true, "nombre": true, "email": true, "foto": true, "idighashtag": true, "hashtag": true, "pk": true, "username": true, "full_name": true, "profile_url": true, "profile_pic_url": true, "follower": true, "following": true, "favorito": true, "update": true, "idprofile": true, "idusuario": false, "url_sub": true, "idseccion": false, "destacado": false, "idseo": false, "url": true, "banner": false, "menu": false, "submenu": false, "idpedidoestado": false, "color": true, "idusuariodireccion": false, "idproductocategoria": false, "url_children": true, "variable": true, "valor": true, "idproducto": false, "texto": false},
                    "detalle": {"usuario": true, "password": true, "estado": true, "titulo": true, "resumen": false, "descripcion": false, "orden": true, "tag": true, "fecha": true, "cantidad": true, "foto": true, "nombre": true, "email": true, "hashtag": true, "following": true, "follower": true, "removed": true, "eficiencia": true, "eficiencia2": true, "total": true, "tipo": true, "telefono": true, "url": false, "subtitulo": true, "archivo": false, "idseccioncategoria": false, "keywords": false, "metadescripcion": false, "destacado": false, "banner": false, "modulo_front": false, "modulo_back": false, "tipo_modulo": false, "link_menu": false, "menu": false, "submenu": false, "color": true, "direccion": true, "idcomuna": true, "villa": true, "edificio": true, "departamento": true, "condominio": true, "casa": true, "empresa": true, "referencias": true, "descuento": false, "descuento_fecha": false, "idpadre": true, "variable": true, "valor": true, "codigo": false, "precio": false, "stock": false, "idproductocategoria": false, "texto": false, "mapa": true}
                },
                "3": {
                    "estado": true,
                    "menu": {"new": true, "excel": false, "regenerar": false},
                    "mostrar": {"usuario": true, "estado": true, "copy": false, "url_detalle": true, "delete": true, "idmediopago": false, "orden": true, "titulo": true, "idigtotal": false, "fecha": true, "tag": true, "cantidad": true, "idadministrador": true, "nombre": true, "email": true, "foto": true, "idighashtag": true, "hashtag": true, "pk": true, "username": true, "full_name": true, "profile_url": true, "profile_pic_url": true, "follower": true, "following": true, "favorito": true, "update": true, "idprofile": true, "idusuario": false, "url_sub": true, "idseccion": false, "destacado": false, "idseo": false, "url": true, "banner": false, "menu": false, "submenu": false, "idpedidoestado": false, "color": true, "idusuariodireccion": false, "idproductocategoria": false, "url_children": true, "variable": true, "valor": true, "idproducto": false, "texto": false},
                    "detalle": {"usuario": true, "password": true, "estado": true, "titulo": true, "resumen": false, "descripcion": false, "orden": true, "tag": true, "fecha": true, "cantidad": true, "foto": true, "nombre": true, "email": true, "hashtag": true, "following": true, "follower": true, "removed": true, "eficiencia": true, "eficiencia2": true, "total": true, "tipo": true, "telefono": true, "url": false, "subtitulo": true, "archivo": false, "idseccioncategoria": false, "keywords": false, "metadescripcion": false, "destacado": false, "banner": false, "modulo_front": false, "modulo_back": false, "tipo_modulo": false, "link_menu": false, "menu": false, "submenu": false, "color": true, "direccion": true, "idcomuna": true, "villa": true, "edificio": true, "departamento": true, "condominio": true, "casa": true, "empresa": true, "referencias": true, "descuento": false, "descuento_fecha": false, "idpadre": true, "variable": true, "valor": true, "codigo": false, "precio": false, "stock": false, "idproductocategoria": false, "texto": false, "mapa": true}
                }
            },
            "orden": 4,
            "aside": true,
            "hijos": false
        }
    ]
}